MANIFEST.in
setup.py
mustachebox/__init__.py
mustachebox/models.py
mustachebox/tests.py
mustachebox/urls.py
mustachebox/views.py
mustachebox.egg-info/PKG-INFO
mustachebox.egg-info/SOURCES.txt
mustachebox.egg-info/dependency_links.txt
mustachebox.egg-info/top_level.txt
mustachebox/backends/__init__.py
mustachebox/backends/base_backend.py
mustachebox/backends/example_backend.py
mustachebox/static/css/cross_filter.css
mustachebox/static/js/area.js
mustachebox/static/js/barchart.js
mustachebox/static/js/columnchart.js
mustachebox/static/js/crossfilter.js
mustachebox/static/js/crossfilter_graph.js
mustachebox/static/js/d3.v2.js
mustachebox/static/js/d3_line_chart.js
mustachebox/static/js/d3_multiline_chart.js
mustachebox/static/js/jquery.js
mustachebox/static/js/pie_chart.js
mustachebox/static/js/time_serie.js
mustachebox/templates/404.html
mustachebox/templates/base.html
mustachebox/templates/mustachebox/all_graph.html
mustachebox/templates/mustachebox/area.html
mustachebox/templates/mustachebox/barchart.html
mustachebox/templates/mustachebox/columnchart.html
mustachebox/templates/mustachebox/crossfilter.html
mustachebox/templates/mustachebox/line_chart.html
mustachebox/templates/mustachebox/multiline_chart.html
mustachebox/templates/mustachebox/pie_chart.html
mustachebox/templates/mustachebox/templatetags_test.html
mustachebox/templates/mustachebox/includes/jsheader.html
mustachebox/templates/mustachebox/tags/area.html
mustachebox/templates/mustachebox/tags/barchart.html
mustachebox/templates/mustachebox/tags/columnchart.html
mustachebox/templates/mustachebox/tags/crossfilter.html
mustachebox/templates/mustachebox/tags/line_chart.html
mustachebox/templates/mustachebox/tags/multiline_chart.html
mustachebox/templates/mustachebox/tags/pie_chart.html
mustachebox/templatetags/__init__.py
mustachebox/templatetags/graph.py