Metadata-Version: 1.1
Name: mustachebox
Version: 0.2
Summary: django framework to create charts of data
Home-page: https://bitbucket.org/boblefrag/mustachebox
Author: Yohann Gabory
Author-email: yohann@gabory.fr
License: UNKNOWN
Download-URL: https://bitbucket.org/boblefrag/mustachebox/get/mustachebox-0.2.tar.gz
Platform: UNKNOWN
Classifier: Development Status :: 4 - Beta
Classifier: Environment :: Web Environment
Classifier: Framework :: Django
Classifier: Intended Audience :: Developers
Classifier: License :: OSI Approved :: GNU General Public License v3 (GPLv3)
Classifier: Programming Language :: Python
Classifier: Operating System :: OS Independent
Classifier: Topic :: Software Development :: Libraries :: Python Modules
Classifier: Topic :: Utilities
Requires: django(>=1.3)
Requires: docutils
